cyc_gbm/__init__.py
cyc_gbm/boosting_tree.py
cyc_gbm/cyc_gbm.py
cyc_gbm/utils/__init__.py
cyc_gbm/utils/distributions.py
cyc_gbm/utils/fix_datatype.py
cyc_gbm/utils/logger.py
cyc_gbm/utils/tuning.py
cyc_gbm-0.0.33.dist-info/LICENSE
cyc_gbm-0.0.33.dist-info/METADATA
cyc_gbm-0.0.33.dist-info/WHEEL
cyc_gbm-0.0.33.dist-info/top_level.txt
cyc_gbm-0.0.33.dist-info/RECORD
