Metadata-Version: 2.1
Name: cyc-gbm
Version: 0.0.33
Summary: A python package for the Cyclic Gradient Boosting Machine algorithm
Home-page: https://github.com/henningzakrisson/cyc-gbm
Author: Henning Zakrisson
Author-email: henning.zakrisson@gmail.com
License: MIT
Classifier: Programming Language :: Python :: 3
Classifier: License :: OSI Approved :: MIT License
Classifier: Operating System :: OS Independent
Requires-Python: >=3.7
License-File: LICENSE
Requires-Dist: matplotlib
Requires-Dist: numpy
Requires-Dist: pandas
Requires-Dist: PyYAML
Requires-Dist: scikit-learn
Requires-Dist: scipy
Requires-Dist: tikzplotlib
Requires-Dist: pytest
